bitquery_pb2_kafka_package-0.2.19.dist-info/licenses/LICENSE
evm/__init__.py
evm/block_message_pb2.py
evm/dex_block_message_pb2.py
evm/dex_pool_block_message_pb2.py
evm/parsed_abi_block_message_pb2.py
evm/token_block_message_pb2.py
price_index/__init__.py
price_index/marketdata_pb2.py
price_index/price_index_pb2.py
solana/__init__.py
solana/block_message_pb2.py
solana/dex_block_message_pb2.py
solana/parsed_idl_block_message_pb2.py
solana/token_block_message_pb2.py
tron/__init__.py
tron/block_message_pb2.py
tron/dex_block_message_pb2.py
tron/parsed_abi_block_message_pb2.py
tron/token_block_message_pb2.py
utxo/__init__.py
utxo/block_message_pb2.py
utxo/parsed_block_message_pb2.py
bitquery_pb2_kafka_package-0.2.19.dist-info/METADATA
bitquery_pb2_kafka_package-0.2.19.dist-info/WHEEL
bitquery_pb2_kafka_package-0.2.19.dist-info/top_level.txt
bitquery_pb2_kafka_package-0.2.19.dist-info/RECORD
