Metadata-Version: 2.4
Name: bitquery-pb2-kafka-package
Version: 0.2.19
Summary: This package contains the pb2 files necessary to interact with Bitquery Kafka Protobuf messages
Author-email: Bitquery <divyasshree@bitquery.io>
License: MIT License
Project-URL: Homepage, https://github.com/bitquery/streaming_protobuf/tree/main
Classifier: Programming Language :: Python :: 3
Classifier: Operating System :: OS Independent
Requires-Python: >=3.6
License-File: LICENSE
Dynamic: license-file
